{"date_published": "2012-08-07", "author": "bhargav", "description": "<div class=\"entry\" id=\"blogbody\">\n            Description: Python based visualization Tool for PLUTO code data.<br/>Homepage URL: <a href=\"http://www.ast.leeds.ac.uk/%7Ephybva/Bhargav_Vaidya/pyCODES.html\">http://www.ast.leeds.ac.uk/~phybva/Bhargav_Vaidya/pyCODES.html</a><br/>Version: 1.1<br/><br/>This is a GUI written to visualize data obtained from a 3D fluid dynamics code called PLUTO [Mignone 2007]. The GUI is based on Python Tkinter package. For screen shots of GUI visualization toolkit and various features check out the Homepage URL. <br/><br/>Repo @ github : https://github.com/coolastro/pyPLUTO.git\n        </div>", "tags": [], "title": "pyPLUTO"}